tadamz_gui/__init__.py
tadamz_gui/gui_functions.py
tadamz_gui/inspect_calibration.py
tadamz_gui/main_gui.py
tadamz_gui/processing_steps.py
tadamz_gui/run_wf.py
tadamz_gui/setup_wf.py
tadamz_gui/assets/Logo.svg
tadamz_gui-0.0.3.dist-info/METADATA
tadamz_gui-0.0.3.dist-info/WHEEL
tadamz_gui-0.0.3.dist-info/entry_points.txt
tadamz_gui-0.0.3.dist-info/licenses/LICENSE
tadamz_gui-0.0.3.dist-info/RECORD
