Metadata-Version: 2.4
Name: tadamz_gui
Version: 0.0.3
Summary: A frontend for the targeted analysis of LC-MS(/MS) data using the tadamz package.
Project-URL: Homepage, https://gitlab.com/j.hemmann/tadamz_gui
Project-URL: Issues, https://gitlab.com/j.hemmann/tadamz_gui/issues
Author-email: Jethro Hemmann <jethro.hemmann@leibniz-hki.de>
License-Expression: MIT
License-File: LICENSE
Classifier: Operating System :: OS Independent
Classifier: Programming Language :: Python :: 3
Requires-Python: >=3.9
Requires-Dist: emzed-gui>=3.0.0a24
Requires-Dist: emzed>=3.0.0a23
Requires-Dist: mplcursors
Requires-Dist: tadamz>=0.12.1
